[{"count":"365","country":"United States","eventName":"game_loaded","versionName":"SoulSilver"},{"count":"292","country":"Philippines","eventName":"game_loaded","versionName":"Emerald"},{"count":"231","country":"United States","eventName":"game_loaded","versionName":"Emerald"},{"count":"176","country":"United States","eventName":"game_loaded","versionName":"Platinum"},{"count":"172","country":"United States","eventName":"game_loaded","versionName":"FireRed"},{"count":"167","country":"United States","eventName":"game_loaded","versionName":"Crystal"},{"count":"126","country":"United States","eventName":"game_loaded","versionName":"Sword"},{"count":"102","country":"Canada","eventName":"game_loaded","versionName":"SoulSilver"},{"count":"82","country":"United States","eventName":"game_loaded","versionName":"X"},{"count":"72","country":"Germany","eventName":"game_loaded","versionName":"Platinum"},{"count":"72","country":"United States","eventName":"game_loaded","versionName":"Black"},{"count":"63","country":"Vietnam","eventName":"game_loaded","versionName":"Violet"},{"count":"57","country":"United States","eventName":"game_loaded","versionName":"Omega Ruby"},{"count":"57","country":"France","eventName":"game_loaded","versionName":"Yellow"},{"count":"55","country":"Bangladesh","eventName":"game_loaded","versionName":"Violet"},{"count":"53","country":"Canada","eventName":"game_loaded","versionName":"Emerald"},{"count":"52","country":"United Kingdom","eventName":"game_loaded","versionName":"SoulSilver"},{"count":"49","country":"United States","eventName":"game_loaded","versionName":"White"},{"count":"47","country":"Malaysia","eventName":"game_loaded","versionName":"SoulSilver"},{"count":"41","country":"United Kingdom","eventName":"game_loaded","versionName":"Sword"},{"count":"41","country":"Taiwan","eventName":"game_loaded","versionName":"Emerald"},{"count":"40","country":"Bangladesh","eventName":"game_loaded","versionName":"Scarlet"},{"count":"39","country":"Indonesia","eventName":"game_loaded","versionName":"X"},{"count":"38","country":"United States","eventName":"game_loaded","versionName":"Ultra Sun"},{"count":"38","country":"Brazil","eventName":"game_loaded","versionName":"SoulSilver"},{"count":"38","country":"Indonesia","eventName":"game_loaded","versionName":"Emerald"},{"count":"35","country":"Spain","eventName":"game_loaded","versionName":"FireRed"},{"count":"35","country":"United States","eventName":"game_loaded","versionName":"White 2"},{"count":"33","country":"United States","eventName":"game_loaded","versionName":"Alpha Sapphire"},{"count":"32","country":"Canada","eventName":"game_loaded","versionName":"FireRed"},{"count":"30","country":"Philippines","eventName":"game_loaded","versionName":"SoulSilver"},{"count":"29","country":"United States","eventName":"game_loaded","versionName":"Black 2"},{"count":"27","country":"Philippines","eventName":"game_loaded","versionName":"Sword"},{"count":"26","country":"United Kingdom","eventName":"game_loaded","versionName":"Emerald"},{"count":"24","country":"Italy","eventName":"game_loaded","versionName":"SoulSilver"},{"count":"24","country":"Brazil","eventName":"game_loaded","versionName":"Emerald"},{"count":"24","country":"Indonesia","eventName":"game_loaded","versionName":"FireRed"},{"count":"23","country":"United States","eventName":"game_loaded","versionName":"Yellow"},{"count":"23","country":"Philippines","eventName":"game_loaded","versionName":"Black 2"},{"count":"22","country":"Indonesia","eventName":"game_loaded","versionName":"Omega Ruby"},{"count":"22","country":"United Kingdom","eventName":"game_loaded","versionName":"Crystal"},{"count":"21","country":"United States","eventName":"game_loaded","versionName":"Scarlet"},{"count":"21","country":"Brazil","eventName":"game_loaded","versionName":"Sword"},{"count":"21","country":"Philippines","eventName":"game_loaded","versionName":"Violet"},{"count":"21","country":"Canada","eventName":"game_loaded","versionName":"Omega Ruby"},{"count":"21","country":"United Kingdom","eventName":"game_loaded","versionName":"White"},{"count":"21","country":"Thailand","eventName":"game_loaded","versionName":"Platinum"},{"count":"20","country":"Indonesia","eventName":"game_loaded","versionName":"SoulSilver"},{"count":"20","country":"Philippines","eventName":"game_loaded","versionName":"Black"},{"count":"20","country":"United States","eventName":"game_loaded","versionName":"Brilliant Diamond"},{"count":"20","country":"Vietnam","eventName":"game_loaded","versionName":"FireRed"},{"count":"19","country":"United Kingdom","eventName":"game_loaded","versionName":"Black 2"},{"count":"19","country":"Vietnam","eventName":"game_loaded","versionName":"Black 2"},{"count":"19","country":"India","eventName":"game_loaded","versionName":"Brilliant Diamond"},{"count":"19","country":"Germany","eventName":"game_loaded","versionName":"Emerald"},{"count":"18","country":"Canada","eventName":"game_loaded","versionName":"Platinum"},{"count":"18","country":"India","eventName":"game_loaded","versionName":"Ultra Sun"},{"count":"17","country":"Japan","eventName":"game_loaded","versionName":"Alpha Sapphire"},{"count":"17","country":"Australia","eventName":"game_loaded","versionName":"Violet"},{"count":"17","country":"Canada","eventName":"game_loaded","versionName":"Sword"},{"count":"16","country":"Dominican Republic","eventName":"game_loaded","versionName":"SoulSilver"},{"count":"16","country":"Japan","eventName":"game_loaded","versionName":"Ultra Moon"},{"count":"16","country":"Ecuador","eventName":"game_loaded","versionName":"Crystal"},{"count":"15","country":"Ecuador","eventName":"game_loaded","versionName":"Platinum"},{"count":"15","country":"Japan","eventName":"game_loaded","versionName":"SoulSilver"},{"count":"15","country":"Germany","eventName":"game_loaded","versionName":"FireRed"},{"count":"15","country":"Brazil","eventName":"game_loaded","versionName":"White"},{"count":"15","country":"Vietnam","eventName":"game_loaded","versionName":"Emerald"},{"count":"15","country":"Philippines","eventName":"game_loaded","versionName":"Omega Ruby"},{"count":"14","country":"United Kingdom","eventName":"game_loaded","versionName":"FireRed"},{"count":"14","country":"India","eventName":"game_loaded","versionName":"Legends: Arceus"},{"count":"14","country":"Brazil","eventName":"game_loaded","versionName":"FireRed"},{"count":"14","country":"United Kingdom","eventName":"game_loaded","versionName":"Ultra Sun"},{"count":"14","country":"United States","eventName":"game_loaded","versionName":"Ultra Moon"},{"count":"14","country":"Italy","eventName":"game_loaded","versionName":"Brilliant Diamond"},{"count":"14","country":"Malaysia","eventName":"game_loaded","versionName":"FireRed"},{"count":"13","country":"France","eventName":"game_loaded","versionName":"SoulSilver"},{"count":"13","country":"Canada","eventName":"game_loaded","versionName":"Black"},{"count":"13","country":"Brazil","eventName":"game_loaded","versionName":"Platinum"},{"count":"13","country":"Spain","eventName":"game_loaded","versionName":"SoulSilver"},{"count":"13","country":"Netherlands","eventName":"game_loaded","versionName":"Ultra Sun"},{"count":"13","country":"Germany","eventName":"game_loaded","versionName":"Ultra Sun"},{"count":"13","country":"Mexico","eventName":"game_loaded","versionName":"FireRed"},{"count":"12","country":"Spain","eventName":"game_loaded","versionName":"Emerald"},{"count":"12","country":"Netherlands","eventName":"game_loaded","versionName":"SoulSilver"},{"count":"12","country":"India","eventName":"game_loaded","versionName":"X"},{"count":"12","country":"Indonesia","eventName":"game_loaded","versionName":"Sword"},{"count":"12","country":"Indonesia","eventName":"game_loaded","versionName":"Ultra Moon"},{"count":"12","country":"Vietnam","eventName":"game_loaded","versionName":"SoulSilver"},{"count":"12","country":"Australia","eventName":"game_loaded","versionName":"Ultra Moon"},{"count":"11","country":"Canada","eventName":"game_loaded","versionName":"Violet"},{"count":"11","country":"Mexico","eventName":"game_loaded","versionName":"SoulSilver"},{"count":"11","country":"Malaysia","eventName":"game_loaded","versionName":"Platinum"},{"count":"11","country":"Mexico","eventName":"game_loaded","versionName":"Black"},{"count":"11","country":"Brazil","eventName":"game_loaded","versionName":"Violet"},{"count":"11","country":"Argentina","eventName":"game_loaded","versionName":"X"},{"count":"11","country":"Italy","eventName":"game_loaded","versionName":"Black 2"},{"count":"11","country":"Germany","eventName":"game_loaded","versionName":"Sword"},{"count":"11","country":"Canada","eventName":"game_loaded","versionName":"Ultra Moon"},{"count":"11","country":"Malaysia","eventName":"game_loaded","versionName":"Black"}]
