[{"count":"572","country":"United States","eventName":"game_loaded","versionName":"SoulSilver"},{"count":"449","country":"United States","eventName":"game_loaded","versionName":"Emerald"},{"count":"432","country":"United States","eventName":"game_loaded","versionName":"FireRed"},{"count":"340","country":"United States","eventName":"game_loaded","versionName":"Platinum"},{"count":"275","country":"Brazil","eventName":"game_loaded","versionName":"Crystal"},{"count":"258","country":"United States","eventName":"game_loaded","versionName":"Sword"},{"count":"195","country":"Brazil","eventName":"game_loaded","versionName":"SoulSilver"},{"count":"186","country":"United States","eventName":"game_loaded","versionName":"Black 2"},{"count":"171","country":"United States","eventName":"game_loaded","versionName":"X"},{"count":"169","country":"Brazil","eventName":"game_loaded","versionName":"FireRed"},{"count":"163","country":"United States","eventName":"game_loaded","versionName":"Ultra Moon"},{"count":"155","country":"United States","eventName":"game_loaded","versionName":"Omega Ruby"},{"count":"148","country":"United States","eventName":"game_loaded","versionName":"White 2"},{"count":"133","country":"United States","eventName":"game_loaded","versionName":"Red"},{"count":"123","country":"Brazil","eventName":"game_loaded","versionName":"Emerald"},{"count":"118","country":"United States","eventName":"game_loaded","versionName":"Ultra Sun"},{"count":"110","country":"United States","eventName":"game_loaded","versionName":"White"},{"count":"95","country":"India","eventName":"game_loaded","versionName":"FireRed"},{"count":"92","country":"India","eventName":"game_loaded","versionName":"Y"},{"count":"90","country":"Colombia","eventName":"game_loaded","versionName":"Emerald"},{"count":"86","country":"United States","eventName":"game_loaded","versionName":"Alpha Sapphire"},{"count":"85","country":"Italy","eventName":"game_loaded","versionName":"SoulSilver"},{"count":"85","country":"Italy","eventName":"game_loaded","versionName":"Platinum"},{"count":"84","country":"United States","eventName":"game_loaded","versionName":"Crystal"},{"count":"83","country":"India","eventName":"game_loaded","versionName":"Emerald"},{"count":"82","country":"Spain","eventName":"game_loaded","versionName":"Sword"},{"count":"77","country":"Indonesia","eventName":"game_loaded","versionName":"Platinum"},{"count":"76","country":"France","eventName":"game_loaded","versionName":"SoulSilver"},{"count":"76","country":"United States","eventName":"game_loaded","versionName":"Black"},{"count":"68","country":"Brazil","eventName":"game_loaded","versionName":"Platinum"},{"count":"67","country":"United Kingdom","eventName":"game_loaded","versionName":"SoulSilver"},{"count":"67","country":"United States","eventName":"game_loaded","versionName":"Y"},{"count":"66","country":"Chile","eventName":"game_loaded","versionName":"Platinum"},{"count":"65","country":"United Kingdom","eventName":"game_loaded","versionName":"FireRed"},{"count":"65","country":"Brazil","eventName":"game_loaded","versionName":"Sword"},{"count":"65","country":"Canada","eventName":"game_loaded","versionName":"SoulSilver"},{"count":"64","country":"Israel","eventName":"game_loaded","versionName":"Y"},{"count":"64","country":"Sweden","eventName":"game_loaded","versionName":"Emerald"},{"count":"62","country":"United States","eventName":"game_loaded","versionName":"Scarlet"},{"count":"59","country":"United Kingdom","eventName":"game_loaded","versionName":"Emerald"},{"count":"59","country":"India","eventName":"game_loaded","versionName":"Ultra Sun"},{"count":"58","country":"Spain","eventName":"game_loaded","versionName":"SoulSilver"},{"count":"57","country":"Italy","eventName":"game_loaded","versionName":"Emerald"},{"count":"56","country":"Peru","eventName":"game_loaded","versionName":"X"},{"count":"55","country":"United States","eventName":"game_loaded","versionName":"Violet"},{"count":"54","country":"United Kingdom","eventName":"game_loaded","versionName":"Platinum"},{"count":"53","country":"India","eventName":"game_loaded","versionName":"SoulSilver"},{"count":"52","country":"Spain","eventName":"game_loaded","versionName":"Emerald"},{"count":"50","country":"Germany","eventName":"game_loaded","versionName":"SoulSilver"},{"count":"50","country":"Spain","eventName":"game_loaded","versionName":"Platinum"},{"count":"47","country":"Indonesia","eventName":"game_loaded","versionName":"SoulSilver"},{"count":"47","country":"Australia","eventName":"game_loaded","versionName":"Platinum"},{"count":"46","country":"India","eventName":"game_loaded","versionName":"Sword"},{"count":"44","country":"Singapore","eventName":"game_loaded","versionName":"Platinum"},{"count":"44","country":"Italy","eventName":"game_loaded","versionName":"FireRed"},{"count":"43","country":"Germany","eventName":"game_loaded","versionName":"Emerald"},{"count":"43","country":"United States","eventName":"game_loaded","versionName":"Yellow"},{"count":"42","country":"France","eventName":"game_loaded","versionName":"Alpha Sapphire"},{"count":"41","country":"Brazil","eventName":"game_loaded","versionName":"X"},{"count":"41","country":"United Kingdom","eventName":"game_loaded","versionName":"Sword"},{"count":"41","country":"Mexico","eventName":"game_loaded","versionName":"Emerald"},{"count":"41","country":"Spain","eventName":"game_loaded","versionName":"FireRed"},{"count":"40","country":"Canada","eventName":"game_loaded","versionName":"Emerald"},{"count":"40","country":"France","eventName":"game_loaded","versionName":"Let's Go, Pikachu!"},{"count":"39","country":"Australia","eventName":"game_loaded","versionName":"SoulSilver"},{"count":"38","country":"France","eventName":"game_loaded","versionName":"Emerald"},{"count":"37","country":"Venezuela","eventName":"game_loaded","versionName":"Emerald"},{"count":"36","country":"Italy","eventName":"game_loaded","versionName":"Legends: Arceus"},{"count":"35","country":"Brazil","eventName":"game_loaded","versionName":"Red"},{"count":"35","country":"Mexico","eventName":"game_loaded","versionName":"SoulSilver"},{"count":"35","country":"Brazil","eventName":"game_loaded","versionName":"Omega Ruby"},{"count":"35","country":"Grenada","eventName":"game_loaded","versionName":"Shield"},{"count":"35","country":"Vietnam","eventName":"game_loaded","versionName":"Emerald"},{"count":"34","country":"Italy","eventName":"game_loaded","versionName":"Sword"},{"count":"34","country":"Peru","eventName":"game_loaded","versionName":"Y"},{"count":"34","country":"Italy","eventName":"game_loaded","versionName":"Omega Ruby"},{"count":"34","country":"Peru","eventName":"game_loaded","versionName":"White"},{"count":"33","country":"India","eventName":"game_loaded","versionName":"Omega Ruby"},{"count":"32","country":"Brazil","eventName":"game_loaded","versionName":"Black 2"},{"count":"32","country":"Netherlands","eventName":"game_loaded","versionName":"SoulSilver"},{"count":"32","country":"Australia","eventName":"game_loaded","versionName":"Emerald"},{"count":"32","country":"France","eventName":"game_loaded","versionName":"X"},{"count":"31","country":"Venezuela","eventName":"game_loaded","versionName":"Ultra Sun"},{"count":"31","country":"Italy","eventName":"game_loaded","versionName":"Y"},{"count":"31","country":"Germany","eventName":"game_loaded","versionName":"FireRed"},{"count":"30","country":"Vietnam","eventName":"game_loaded","versionName":"FireRed"},{"count":"29","country":"Mexico","eventName":"game_loaded","versionName":"Sword"},{"count":"29","country":"Argentina","eventName":"game_loaded","versionName":"FireRed"},{"count":"28","country":"Indonesia","eventName":"game_loaded","versionName":"Violet"},{"count":"28","country":"Philippines","eventName":"game_loaded","versionName":"Emerald"},{"count":"28","country":"Canada","eventName":"game_loaded","versionName":"FireRed"},{"count":"28","country":"Malaysia","eventName":"game_loaded","versionName":"X"},{"count":"28","country":"Germany","eventName":"game_loaded","versionName":"Alpha Sapphire"},{"count":"27","country":"France","eventName":"game_loaded","versionName":"Platinum"},{"count":"27","country":"Italy","eventName":"game_loaded","versionName":"Ultra Sun"},{"count":"26","country":"Canada","eventName":"game_loaded","versionName":"Violet"},{"count":"26","country":"United States","eventName":"game_loaded","versionName":"Brilliant Diamond"},{"count":"26","country":"Mexico","eventName":"game_loaded","versionName":"Ultra Sun"},{"count":"26","country":"Türkiye","eventName":"game_loaded","versionName":"Let's Go, Pikachu!"},{"count":"25","country":"Germany","eventName":"game_loaded","versionName":"Sword"}]
