[{"count":"2186","country":"United States","eventName":"game_loaded","versionName":"FireRed"},{"count":"1941","country":"Brazil","eventName":"game_loaded","versionName":"FireRed"},{"count":"1828","country":"United States","eventName":"game_loaded","versionName":"SoulSilver"},{"count":"1793","country":"United States","eventName":"game_loaded","versionName":"Emerald"},{"count":"1406","country":"Brazil","eventName":"game_loaded","versionName":"SoulSilver"},{"count":"1153","country":"Brazil","eventName":"game_loaded","versionName":"Emerald"},{"count":"1094","country":"United States","eventName":"game_loaded","versionName":"Platinum"},{"count":"838","country":"Brazil","eventName":"game_loaded","versionName":"Platinum"},{"count":"786","country":"United States","eventName":"game_loaded","versionName":"Sword"},{"count":"712","country":"Italy","eventName":"game_loaded","versionName":"SoulSilver"},{"count":"682","country":"Brazil","eventName":"game_loaded","versionName":"Sword"},{"count":"663","country":"United States","eventName":"game_loaded","versionName":"Omega Ruby"},{"count":"568","country":"Germany","eventName":"game_loaded","versionName":"SoulSilver"},{"count":"556","country":"Australia","eventName":"game_loaded","versionName":"Emerald"},{"count":"550","country":"Spain","eventName":"game_loaded","versionName":"Platinum"},{"count":"520","country":"Spain","eventName":"game_loaded","versionName":"Omega Ruby"},{"count":"492","country":"Spain","eventName":"game_loaded","versionName":"SoulSilver"},{"count":"488","country":"United States","eventName":"game_loaded","versionName":"Black 2"},{"count":"463","country":"Italy","eventName":"game_loaded","versionName":"Emerald"},{"count":"442","country":"Italy","eventName":"game_loaded","versionName":"FireRed"},{"count":"424","country":"Mexico","eventName":"game_loaded","versionName":"FireRed"},{"count":"418","country":"Mexico","eventName":"game_loaded","versionName":"Emerald"},{"count":"417","country":"United States","eventName":"game_loaded","versionName":"Crystal"},{"count":"407","country":"United Kingdom","eventName":"game_loaded","versionName":"FireRed"},{"count":"400","country":"France","eventName":"game_loaded","versionName":"SoulSilver"},{"count":"373","country":"United States","eventName":"game_loaded","versionName":"White 2"},{"count":"371","country":"United States","eventName":"game_loaded","versionName":"Black"},{"count":"362","country":"France","eventName":"game_loaded","versionName":"FireRed"},{"count":"361","country":"Italy","eventName":"game_loaded","versionName":"Platinum"},{"count":"346","country":"Brazil","eventName":"game_loaded","versionName":"Omega Ruby"},{"count":"340","country":"United Kingdom","eventName":"game_loaded","versionName":"Emerald"},{"count":"327","country":"Mexico","eventName":"game_loaded","versionName":"SoulSilver"},{"count":"314","country":"Brazil","eventName":"game_loaded","versionName":"Ultra Moon"},{"count":"307","country":"South Korea","eventName":"game_loaded","versionName":"SoulSilver"},{"count":"295","country":"France","eventName":"game_loaded","versionName":"Emerald"},{"count":"292","country":"Philippines","eventName":"game_loaded","versionName":"SoulSilver"},{"count":"290","country":"Germany","eventName":"game_loaded","versionName":"Black 2"},{"count":"283","country":"United States","eventName":"game_loaded","versionName":"Ultra Sun"},{"count":"280","country":"Brazil","eventName":"game_loaded","versionName":"White"},{"count":"278","country":"Spain","eventName":"game_loaded","versionName":"Emerald"},{"count":"270","country":"South Korea","eventName":"game_loaded","versionName":"Black 2"},{"count":"260","country":"France","eventName":"game_loaded","versionName":"Platinum"},{"count":"255","country":"United Kingdom","eventName":"game_loaded","versionName":"SoulSilver"},{"count":"251","country":"Brazil","eventName":"game_loaded","versionName":"X"},{"count":"250","country":"Brazil","eventName":"game_loaded","versionName":"Alpha Sapphire"},{"count":"246","country":"Germany","eventName":"game_loaded","versionName":"FireRed"},{"count":"240","country":"Spain","eventName":"game_loaded","versionName":"FireRed"},{"count":"240","country":"Canada","eventName":"game_loaded","versionName":"FireRed"},{"count":"239","country":"Chile","eventName":"game_loaded","versionName":"SoulSilver"},{"count":"235","country":"Brazil","eventName":"game_loaded","versionName":"White 2"},{"count":"234","country":"United States","eventName":"game_loaded","versionName":"White"},{"count":"231","country":"United States","eventName":"game_loaded","versionName":"X"},{"count":"230","country":"Brazil","eventName":"game_loaded","versionName":"Ultra Sun"},{"count":"230","country":"United States","eventName":"game_loaded","versionName":"Ultra Moon"},{"count":"228","country":"Mexico","eventName":"game_loaded","versionName":"Platinum"},{"count":"225","country":"Spain","eventName":"game_loaded","versionName":"Alpha Sapphire"},{"count":"223","country":"India","eventName":"game_loaded","versionName":"Sword"},{"count":"213","country":"Spain","eventName":"game_loaded","versionName":"Sword"},{"count":"212","country":"Brazil","eventName":"game_loaded","versionName":"Black 2"},{"count":"212","country":"Philippines","eventName":"game_loaded","versionName":"FireRed"},{"count":"210","country":"Chile","eventName":"game_loaded","versionName":"Emerald"},{"count":"209","country":"Mexico","eventName":"game_loaded","versionName":"Omega Ruby"},{"count":"208","country":"Spain","eventName":"game_loaded","versionName":"Black"},{"count":"208","country":"Mexico","eventName":"game_loaded","versionName":"Ultra Sun"},{"count":"207","country":"Philippines","eventName":"game_loaded","versionName":"Emerald"},{"count":"206","country":"United States","eventName":"game_loaded","versionName":"Yellow"},{"count":"205","country":"United States","eventName":"game_loaded","versionName":"Red"},{"count":"204","country":"United States","eventName":"game_loaded","versionName":"Alpha Sapphire"},{"count":"201","country":"Italy","eventName":"game_loaded","versionName":"Black 2"},{"count":"198","country":"Canada","eventName":"game_loaded","versionName":"Emerald"},{"count":"195","country":"Germany","eventName":"game_loaded","versionName":"Emerald"},{"count":"191","country":"Germany","eventName":"game_loaded","versionName":"Platinum"},{"count":"189","country":"Brazil","eventName":"game_loaded","versionName":"Black"},{"count":"186","country":"Argentina","eventName":"game_loaded","versionName":"FireRed"},{"count":"186","country":"United States","eventName":"game_loaded","versionName":"Y"},{"count":"182","country":"Chile","eventName":"game_loaded","versionName":"Omega Ruby"},{"count":"181","country":"Brazil","eventName":"game_loaded","versionName":"Y"},{"count":"178","country":"Spain","eventName":"game_loaded","versionName":"White"},{"count":"171","country":"Mexico","eventName":"game_loaded","versionName":"Sword"},{"count":"170","country":"India","eventName":"game_loaded","versionName":"FireRed"},{"count":"170","country":"Argentina","eventName":"game_loaded","versionName":"Emerald"},{"count":"166","country":"France","eventName":"game_loaded","versionName":"Sword"},{"count":"162","country":"Spain","eventName":"game_loaded","versionName":"Ultra Moon"},{"count":"161","country":"Argentina","eventName":"game_loaded","versionName":"Omega Ruby"},{"count":"161","country":"India","eventName":"game_loaded","versionName":"Emerald"},{"count":"160","country":"Venezuela","eventName":"game_loaded","versionName":"Emerald"},{"count":"160","country":"Portugal","eventName":"game_loaded","versionName":"Emerald"},{"count":"158","country":"Chile","eventName":"game_loaded","versionName":"FireRed"},{"count":"157","country":"Spain","eventName":"game_loaded","versionName":"Ultra Sun"},{"count":"157","country":"South Korea","eventName":"game_loaded","versionName":"Sword"},{"count":"155","country":"Australia","eventName":"game_loaded","versionName":"SoulSilver"},{"count":"154","country":"Venezuela","eventName":"game_loaded","versionName":"SoulSilver"},{"count":"154","country":"Spain","eventName":"game_loaded","versionName":"X"},{"count":"154","country":"United Kingdom","eventName":"game_loaded","versionName":"Platinum"},{"count":"153","country":"Argentina","eventName":"game_loaded","versionName":"SoulSilver"},{"count":"152","country":"Colombia","eventName":"game_loaded","versionName":"Omega Ruby"},{"count":"144","country":"Chile","eventName":"game_loaded","versionName":"Platinum"},{"count":"139","country":"Mexico","eventName":"game_loaded","versionName":"White 2"},{"count":"134","country":"Vietnam","eventName":"game_loaded","versionName":"Omega Ruby"},{"count":"132","country":"Italy","eventName":"game_loaded","versionName":"Sword"}]
