[{"count":"249","country":"United States","eventName":"game_loaded","versionName":"SoulSilver"},{"count":"143","country":"United States","eventName":"game_loaded","versionName":"Emerald"},{"count":"127","country":"United States","eventName":"game_loaded","versionName":"FireRed"},{"count":"126","country":"United States","eventName":"game_loaded","versionName":"Platinum"},{"count":"103","country":"United States","eventName":"game_loaded","versionName":"Sword"},{"count":"82","country":"Canada","eventName":"game_loaded","versionName":"SoulSilver"},{"count":"63","country":"United States","eventName":"game_loaded","versionName":"X"},{"count":"59","country":"Germany","eventName":"game_loaded","versionName":"Platinum"},{"count":"51","country":"Vietnam","eventName":"game_loaded","versionName":"FireRed"},{"count":"48","country":"United States","eventName":"game_loaded","versionName":"Black"},{"count":"45","country":"United States","eventName":"game_loaded","versionName":"Ultra Moon"},{"count":"44","country":"Bangladesh","eventName":"game_loaded","versionName":"Violet"},{"count":"43","country":"United States","eventName":"game_loaded","versionName":"Crystal"},{"count":"43","country":"France","eventName":"game_loaded","versionName":"SoulSilver"},{"count":"43","country":"United States","eventName":"game_loaded","versionName":"White"},{"count":"38","country":"Brazil","eventName":"game_loaded","versionName":"Emerald"},{"count":"38","country":"France","eventName":"game_loaded","versionName":"Yellow"},{"count":"37","country":"United Kingdom","eventName":"game_loaded","versionName":"SoulSilver"},{"count":"37","country":"United States","eventName":"game_loaded","versionName":"Black 2"},{"count":"36","country":"Canada","eventName":"game_loaded","versionName":"Emerald"},{"count":"36","country":"Taiwan","eventName":"game_loaded","versionName":"Emerald"},{"count":"35","country":"Malaysia","eventName":"game_loaded","versionName":"SoulSilver"},{"count":"35","country":"United States","eventName":"game_loaded","versionName":"Omega Ruby"},{"count":"34","country":"Germany","eventName":"game_loaded","versionName":"Crystal"},{"count":"33","country":"United Kingdom","eventName":"game_loaded","versionName":"Sword"},{"count":"29","country":"United Kingdom","eventName":"game_loaded","versionName":"Emerald"},{"count":"29","country":"United States","eventName":"game_loaded","versionName":"Alpha Sapphire"},{"count":"28","country":"Japan","eventName":"game_loaded","versionName":"Alpha Sapphire"},{"count":"27","country":"United Kingdom","eventName":"game_loaded","versionName":"Black 2"},{"count":"27","country":"United States","eventName":"game_loaded","versionName":"Yellow"},{"count":"27","country":"United States","eventName":"game_loaded","versionName":"White 2"},{"count":"26","country":"Italy","eventName":"game_loaded","versionName":"SoulSilver"},{"count":"25","country":"Indonesia","eventName":"game_loaded","versionName":"X"},{"count":"24","country":"United Kingdom","eventName":"game_loaded","versionName":"Crystal"},{"count":"24","country":"Indonesia","eventName":"game_loaded","versionName":"Sword"},{"count":"23","country":"Thailand","eventName":"game_loaded","versionName":"Black 2"},{"count":"23","country":"Germany","eventName":"game_loaded","versionName":"Emerald"},{"count":"22","country":"United Kingdom","eventName":"game_loaded","versionName":"FireRed"},{"count":"22","country":"Indonesia","eventName":"game_loaded","versionName":"Emerald"},{"count":"21","country":"Canada","eventName":"game_loaded","versionName":"Omega Ruby"},{"count":"21","country":"Spain","eventName":"game_loaded","versionName":"FireRed"},{"count":"21","country":"Brazil","eventName":"game_loaded","versionName":"FireRed"},{"count":"20","country":"Singapore","eventName":"game_loaded","versionName":"FireRed"},{"count":"20","country":"South Korea","eventName":"game_loaded","versionName":"SoulSilver"},{"count":"20","country":"Brazil","eventName":"game_loaded","versionName":"SoulSilver"},{"count":"20","country":"United States","eventName":"game_loaded","versionName":"Red"},{"count":"19","country":"Indonesia","eventName":"game_loaded","versionName":"Scarlet"},{"count":"19","country":"United States","eventName":"game_loaded","versionName":"Violet"},{"count":"19","country":"Philippines","eventName":"game_loaded","versionName":"Sword"},{"count":"19","country":"Philippines","eventName":"game_loaded","versionName":"Violet"},{"count":"19","country":"Mexico","eventName":"game_loaded","versionName":"Black"},{"count":"17","country":"Thailand","eventName":"game_loaded","versionName":"Platinum"},{"count":"16","country":"Brazil","eventName":"game_loaded","versionName":"Sword"},{"count":"16","country":"Canada","eventName":"game_loaded","versionName":"Platinum"},{"count":"16","country":"Vietnam","eventName":"game_loaded","versionName":"SoulSilver"},{"count":"16","country":"Germany","eventName":"game_loaded","versionName":"FireRed"},{"count":"16","country":"Cuba","eventName":"game_loaded","versionName":"Ultra Sun"},{"count":"16","country":"Ecuador","eventName":"game_loaded","versionName":"Crystal"},{"count":"15","country":"Netherlands","eventName":"game_loaded","versionName":"SoulSilver"},{"count":"15","country":"Spain","eventName":"game_loaded","versionName":"SoulSilver"},{"count":"14","country":"United Kingdom","eventName":"game_loaded","versionName":"Ultra Sun"},{"count":"14","country":"India","eventName":"game_loaded","versionName":"Omega Ruby"},{"count":"14","country":"Canada","eventName":"game_loaded","versionName":"FireRed"},{"count":"14","country":"Japan","eventName":"game_loaded","versionName":"SoulSilver"},{"count":"14","country":"Australia","eventName":"game_loaded","versionName":"Violet"},{"count":"14","country":"Vietnam","eventName":"game_loaded","versionName":"Emerald"},{"count":"14","country":"Netherlands","eventName":"game_loaded","versionName":"Emerald"},{"count":"14","country":"Vietnam","eventName":"game_loaded","versionName":"Omega Ruby"},{"count":"13","country":"Germany","eventName":"game_loaded","versionName":"Sword"},{"count":"13","country":"Mexico","eventName":"game_loaded","versionName":"Platinum"},{"count":"13","country":"South Korea","eventName":"game_loaded","versionName":"Omega Ruby"},{"count":"12","country":"United States","eventName":"game_loaded","versionName":"Ultra Sun"},{"count":"12","country":"Ecuador","eventName":"game_loaded","versionName":"Platinum"},{"count":"12","country":"Vietnam","eventName":"game_loaded","versionName":"Black 2"},{"count":"12","country":"Mexico","eventName":"game_loaded","versionName":"FireRed"},{"count":"12","country":"Vietnam","eventName":"game_loaded","versionName":"Sword"},{"count":"12","country":"Türkiye","eventName":"game_loaded","versionName":"Scarlet"},{"count":"11","country":"Germany","eventName":"game_loaded","versionName":"SoulSilver"},{"count":"11","country":"Canada","eventName":"game_loaded","versionName":"Black"},{"count":"11","country":"Canada","eventName":"game_loaded","versionName":"Ultra Moon"},{"count":"11","country":"Argentina","eventName":"game_loaded","versionName":"X"},{"count":"11","country":"Philippines","eventName":"game_loaded","versionName":"Emerald"},{"count":"11","country":"Netherlands","eventName":"game_loaded","versionName":"Sword"},{"count":"11","country":"Australia","eventName":"game_loaded","versionName":"Platinum"},{"count":"11","country":"United Kingdom","eventName":"game_loaded","versionName":"Omega Ruby"},{"count":"11","country":"Australia","eventName":"game_loaded","versionName":"Ultra Sun"},{"count":"11","country":"Philippines","eventName":"game_loaded","versionName":"Omega Ruby"},{"count":"10","country":"India","eventName":"game_loaded","versionName":"X"},{"count":"10","country":"Malaysia","eventName":"game_loaded","versionName":"Platinum"},{"count":"10","country":"Spain","eventName":"game_loaded","versionName":"Emerald"},{"count":"10","country":"Australia","eventName":"game_loaded","versionName":"SoulSilver"},{"count":"10","country":"Vietnam","eventName":"game_loaded","versionName":"White 2"},{"count":"10","country":"Canada","eventName":"game_loaded","versionName":"Yellow"},{"count":"10","country":"Netherlands","eventName":"game_loaded","versionName":"Ultra Sun"},{"count":"10","country":"Canada","eventName":"game_loaded","versionName":"Sword"},{"count":"10","country":"Canada","eventName":"game_loaded","versionName":"X"},{"count":"9","country":"Brazil","eventName":"game_loaded","versionName":"Platinum"},{"count":"9","country":"Germany","eventName":"game_loaded","versionName":"Ultra Sun"},{"count":"9","country":"South Korea","eventName":"game_loaded","versionName":"Sword"},{"count":"9","country":"India","eventName":"game_loaded","versionName":"Brilliant Diamond"}]
