[{"count":"330","country":"United States","eventName":"item_modified","itemId":"50","quantityAverage":"820.5848484848485","quantityMax":"999","quantityMin":"1"},{"count":"307","country":"Spain","eventName":"item_modified","itemId":"50","quantityAverage":"937.6579804560259","quantityMax":"999","quantityMin":"10"},{"count":"256","country":"Germany","eventName":"item_modified","itemId":"50","quantityAverage":"896.73828125","quantityMax":"999","quantityMin":"1"},{"count":"202","country":"United States","eventName":"item_modified","itemId":"68","quantityAverage":"534.7821782178216","quantityMax":"999","quantityMin":"1"},{"count":"152","country":"United States","eventName":"item_modified","itemId":"1","quantityAverage":"391.6578947368422","quantityMax":"999","quantityMin":"1"},{"count":"122","country":"Mexico","eventName":"item_modified","itemId":"50","quantityAverage":"937.9508196721312","quantityMax":"999","quantityMin":"30"},{"count":"106","country":"Chile","eventName":"item_modified","itemId":"50","quantityAverage":"936.1792452830189","quantityMax":"999","quantityMin":"99"},{"count":"101","country":"Colombia","eventName":"item_modified","itemId":"50","quantityAverage":"939.6831683168318","quantityMax":"999","quantityMin":"10"},{"count":"98","country":"Brazil","eventName":"item_modified","itemId":"50","quantityAverage":"676.6020408163265","quantityMax":"999","quantityMin":"1"},{"count":"90","country":"Italy","eventName":"item_modified","itemId":"50","quantityAverage":"945.2888888888887","quantityMax":"999","quantityMin":"36"},{"count":"84","country":"United States","eventName":"item_modified","itemId":"23","quantityAverage":"747.1547619047619","quantityMax":"999","quantityMin":"50"},{"count":"84","country":"Brazil","eventName":"item_modified","itemId":"1","quantityAverage":"353.11904761904765","quantityMax":"999","quantityMin":"1"},{"count":"80","country":"United Kingdom","eventName":"item_modified","itemId":"50","quantityAverage":"764.9749999999999","quantityMax":"999","quantityMin":"1"},{"count":"80","country":"Germany","eventName":"item_modified","itemId":"1","quantityAverage":"483.42499999999995","quantityMax":"999","quantityMin":"1"},{"count":"78","country":"Argentina","eventName":"item_modified","itemId":"50","quantityAverage":"894.8974358974361","quantityMax":"999","quantityMin":"4"},{"count":"69","country":"United States","eventName":"item_modified","itemId":"2","quantityAverage":"327.9130434782609","quantityMax":"999","quantityMin":"9"},{"count":"67","country":"Brazil","eventName":"item_modified","itemId":"68","quantityAverage":"549.4328358208957","quantityMax":"999","quantityMin":"8"},{"count":"57","country":"India","eventName":"item_modified","itemId":"50","quantityAverage":"789.0877192982455","quantityMax":"999","quantityMin":"5"},{"count":"55","country":"United Kingdom","eventName":"item_modified","itemId":"68","quantityAverage":"769.1636363636363","quantityMax":"999","quantityMin":"5"},{"count":"55","country":"Spain","eventName":"item_modified","itemId":"1","quantityAverage":"634.2363636363635","quantityMax":"999","quantityMin":"0"},{"count":"54","country":"Germany","eventName":"item_modified","itemId":"68","quantityAverage":"496.1666666666667","quantityMax":"999","quantityMin":"1"},{"count":"53","country":"United States","eventName":"item_modified","itemId":"29","quantityAverage":"569.188679245283","quantityMax":"999","quantityMin":"6"},{"count":"52","country":"United States","eventName":"item_modified","itemId":"77","quantityAverage":"764.4615384615386","quantityMax":"999","quantityMin":"1"},{"count":"52","country":"Spain","eventName":"item_modified","itemId":"93","quantityAverage":"590.0961538461539","quantityMax":"999","quantityMin":"1"},{"count":"50","country":"United States","eventName":"item_modified","itemId":"84","quantityAverage":"280.23999999999995","quantityMax":"999","quantityMin":"1"},{"count":"48","country":"Venezuela","eventName":"item_modified","itemId":"50","quantityAverage":"739.0208333333333","quantityMax":"999","quantityMin":"30"},{"count":"47","country":"United States","eventName":"item_modified","itemId":"4","quantityAverage":"298.82978723404256","quantityMax":"999","quantityMin":"1"},{"count":"46","country":"Canada","eventName":"item_modified","itemId":"50","quantityAverage":"848.6739130434781","quantityMax":"999","quantityMin":"30"},{"count":"45","country":"United States","eventName":"item_modified","itemId":"41","quantityAverage":"516.6222222222221","quantityMax":"999","quantityMin":"1"},{"count":"45","country":"United States","eventName":"item_modified","itemId":"340","quantityAverage":"13.600000000000005","quantityMax":"99","quantityMin":"1"},{"count":"44","country":"United States","eventName":"item_modified","itemId":"53","quantityAverage":"734.2727272727271","quantityMax":"999","quantityMin":"25"},{"count":"43","country":"Mexico","eventName":"item_modified","itemId":"68","quantityAverage":"524.8837209302326","quantityMax":"999","quantityMin":"1"},{"count":"42","country":"United States","eventName":"item_modified","itemId":"351","quantityAverage":"9.833333333333336","quantityMax":"99","quantityMin":"1"},{"count":"41","country":"United States","eventName":"item_modified","itemId":"93","quantityAverage":"320.5609756097561","quantityMax":"999","quantityMin":"1"},{"count":"41","country":"United States","eventName":"item_modified","itemId":"25","quantityAverage":"364.43902439024384","quantityMax":"999","quantityMin":"5"},{"count":"40","country":"United States","eventName":"item_modified","itemId":"32","quantityAverage":"206.1","quantityMax":"999","quantityMin":"30"},{"count":"40","country":"India","eventName":"item_modified","itemId":"1","quantityAverage":"690.325","quantityMax":"999","quantityMin":"2"},{"count":"39","country":"France","eventName":"item_modified","itemId":"1","quantityAverage":"501.20512820512835","quantityMax":"999","quantityMin":"1"},{"count":"39","country":"United States","eventName":"item_modified","itemId":"19","quantityAverage":"480.69230769230774","quantityMax":"999","quantityMin":"12"},{"count":"39","country":"Peru","eventName":"item_modified","itemId":"50","quantityAverage":"913.974358974359","quantityMax":"999","quantityMin":"50"},{"count":"37","country":"United Kingdom","eventName":"item_modified","itemId":"1","quantityAverage":"561.8918918918918","quantityMax":"999","quantityMin":"1"},{"count":"36","country":"Ecuador","eventName":"item_modified","itemId":"50","quantityAverage":"956.8888888888888","quantityMax":"999","quantityMin":"99"},{"count":"35","country":"United States","eventName":"item_modified","itemId":"158","quantityAverage":"587.3142857142858","quantityMax":"999","quantityMin":"45"},{"count":"34","country":"France","eventName":"item_modified","itemId":"50","quantityAverage":"817.7647058823529","quantityMax":"999","quantityMin":"20"},{"count":"34","country":"United States","eventName":"item_modified","itemId":"301","quantityAverage":"51.1764705882353","quantityMax":"990","quantityMin":"1"},{"count":"33","country":"United States","eventName":"item_modified","itemId":"353","quantityAverage":"6.3939393939393945","quantityMax":"99","quantityMin":"1"},{"count":"33","country":"Spain","eventName":"item_modified","itemId":"68","quantityAverage":"675.0909090909091","quantityMax":"999","quantityMin":"6"},{"count":"32","country":"United States","eventName":"item_modified","itemId":"312","quantityAverage":"48.65625000000001","quantityMax":"990","quantityMin":"1"},{"count":"32","country":"Italy","eventName":"item_modified","itemId":"1","quantityAverage":"587.0625","quantityMax":"999","quantityMin":"1"},{"count":"32","country":"Brazil","eventName":"item_modified","itemId":"2","quantityAverage":"402.4687500000001","quantityMax":"999","quantityMin":"25"},{"count":"32","country":"United States","eventName":"item_modified","itemId":"362","quantityAverage":"9.875","quantityMax":"99","quantityMin":"1"},{"count":"31","country":"Chile","eventName":"item_modified","itemId":"93","quantityAverage":"747.8064516129031","quantityMax":"999","quantityMin":"1"},{"count":"31","country":"United States","eventName":"item_modified","itemId":"323","quantityAverage":"24.516129032258064","quantityMax":"99","quantityMin":"1"},{"count":"30","country":"United States","eventName":"item_modified","itemId":"45","quantityAverage":"409.3666666666666","quantityMax":"999","quantityMin":"1"},{"count":"30","country":"United States","eventName":"item_modified","itemId":"329","quantityAverage":"27.0","quantityMax":"500","quantityMin":"1"},{"count":"30","country":"Italy","eventName":"item_modified","itemId":"68","quantityAverage":"538.8666666666667","quantityMax":"999","quantityMin":"5"},{"count":"30","country":"United States","eventName":"item_modified","itemId":"24","quantityAverage":"496.0666666666667","quantityMax":"999","quantityMin":"9"},{"count":"30","country":"United States","eventName":"item_modified","itemId":"3","quantityAverage":"277.3666666666667","quantityMax":"999","quantityMin":"1"},{"count":"29","country":"United States","eventName":"item_modified","itemId":"48","quantityAverage":"307.8275862068965","quantityMax":"999","quantityMin":"1"},{"count":"29","country":"United States","eventName":"item_modified","itemId":"107","quantityAverage":"46.82758620689654","quantityMax":"999","quantityMin":"1"},{"count":"29","country":"Spain","eventName":"item_modified","itemId":"77","quantityAverage":"850.551724137931","quantityMax":"999","quantityMin":"50"},{"count":"28","country":"United States","eventName":"item_modified","itemId":"40","quantityAverage":"268.3571428571429","quantityMax":"999","quantityMin":"1"},{"count":"28","country":"Brazil","eventName":"item_modified","itemId":"107","quantityAverage":"168.9642857142857","quantityMax":"999","quantityMin":"1"},{"count":"28","country":"Netherlands","eventName":"item_modified","itemId":"50","quantityAverage":"760.5714285714286","quantityMax":"999","quantityMin":"10"},{"count":"27","country":"United States","eventName":"item_modified","itemId":"157","quantityAverage":"328.8148148148148","quantityMax":"999","quantityMin":"20"},{"count":"27","country":"United States","eventName":"item_modified","itemId":"318","quantityAverage":"24.185185185185183","quantityMax":"99","quantityMin":"1"},{"count":"27","country":"United States","eventName":"item_modified","itemId":"328","quantityAverage":"18.629629629629626","quantityMax":"99","quantityMin":"1"},{"count":"27","country":"Mexico","eventName":"item_modified","itemId":"1","quantityAverage":"279.85185185185185","quantityMax":"999","quantityMin":"5"},{"count":"27","country":"United States","eventName":"item_modified","itemId":"331","quantityAverage":"16.77777777777778","quantityMax":"99","quantityMin":"1"},{"count":"26","country":"Canada","eventName":"item_modified","itemId":"1","quantityAverage":"389.50000000000006","quantityMax":"999","quantityMin":"1"},{"count":"26","country":"Spain","eventName":"item_modified","itemId":"645","quantityAverage":"283.88461538461536","quantityMax":"999","quantityMin":"1"},{"count":"26","country":"Austria","eventName":"item_modified","itemId":"50","quantityAverage":"952.9615384615385","quantityMax":"999","quantityMin":"99"},{"count":"26","country":"United States","eventName":"item_modified","itemId":"49","quantityAverage":"448.0384615384615","quantityMax":"999","quantityMin":"10"},{"count":"26","country":"Spain","eventName":"item_modified","itemId":"23","quantityAverage":"634.7692307692307","quantityMax":"999","quantityMin":"2"},{"count":"26","country":"United States","eventName":"item_modified","itemId":"46","quantityAverage":"489.96153846153845","quantityMax":"999","quantityMin":"10"},{"count":"25","country":"United States","eventName":"item_modified","itemId":"6","quantityAverage":"289.96000000000004","quantityMax":"999","quantityMin":"1"},{"count":"25","country":"Canada","eventName":"item_modified","itemId":"158","quantityAverage":"999.0","quantityMax":"999","quantityMin":"999"},{"count":"25","country":"United States","eventName":"item_modified","itemId":"234","quantityAverage":"248.83999999999997","quantityMax":"999","quantityMin":"1"},{"count":"25","country":"Canada","eventName":"item_modified","itemId":"157","quantityAverage":"999.0","quantityMax":"999","quantityMin":"999"},{"count":"24","country":"United States","eventName":"item_modified","itemId":"335","quantityAverage":"26.54166666666667","quantityMax":"99","quantityMin":"1"},{"count":"24","country":"United Kingdom","eventName":"item_modified","itemId":"23","quantityAverage":"586.4166666666666","quantityMax":"999","quantityMin":"1"},{"count":"24","country":"United States","eventName":"item_modified","itemId":"356","quantityAverage":"18.083333333333336","quantityMax":"99","quantityMin":"1"},{"count":"24","country":"United States","eventName":"item_modified","itemId":"52","quantityAverage":"441.99999999999994","quantityMax":"999","quantityMin":"9"},{"count":"24","country":"United States","eventName":"item_modified","itemId":"169","quantityAverage":"504.3333333333333","quantityMax":"999","quantityMin":"1"},{"count":"24","country":"Ireland","eventName":"item_modified","itemId":"68","quantityAverage":"924.0","quantityMax":"999","quantityMin":"99"},{"count":"23","country":"United States","eventName":"item_modified","itemId":"81","quantityAverage":"115.17391304347824","quantityMax":"999","quantityMin":"1"},{"count":"23","country":"United States","eventName":"item_modified","itemId":"15","quantityAverage":"452.78260869565213","quantityMax":"999","quantityMin":"50"},{"count":"23","country":"United States","eventName":"item_modified","itemId":"11","quantityAverage":"339.47826086956525","quantityMax":"999","quantityMin":"1"},{"count":"23","country":"Germany","eventName":"item_modified","itemId":"77","quantityAverage":"775.3478260869565","quantityMax":"999","quantityMin":"50"},{"count":"23","country":"United States","eventName":"item_modified","itemId":"197","quantityAverage":"104.0434782608696","quantityMax":"999","quantityMin":"1"},{"count":"23","country":"United States","eventName":"item_modified","itemId":"12","quantityAverage":"203.56521739130434","quantityMax":"999","quantityMin":"2"},{"count":"22","country":"United States","eventName":"item_modified","itemId":"155","quantityAverage":"543.3636363636364","quantityMax":"999","quantityMin":"15"},{"count":"22","country":"United States","eventName":"item_modified","itemId":"632","quantityAverage":"46.409090909090914","quantityMax":"999","quantityMin":"1"},{"count":"22","country":"Colombia","eventName":"item_modified","itemId":"93","quantityAverage":"685.8181818181819","quantityMax":"999","quantityMin":"20"},{"count":"22","country":"India","eventName":"item_modified","itemId":"29","quantityAverage":"775.6363636363636","quantityMax":"999","quantityMin":"69"},{"count":"22","country":"Germany","eventName":"item_modified","itemId":"23","quantityAverage":"747.2272727272727","quantityMax":"999","quantityMin":"50"},{"count":"22","country":"United States","eventName":"item_modified","itemId":"27","quantityAverage":"395.31818181818176","quantityMax":"999","quantityMin":"30"},{"count":"22","country":"United States","eventName":"item_modified","itemId":"216","quantityAverage":"62.36363636363636","quantityMax":"999","quantityMin":"1"},{"count":"21","country":"Germany","eventName":"item_modified","itemId":"2","quantityAverage":"644.2857142857142","quantityMax":"999","quantityMin":"1"},{"count":"21","country":"France","eventName":"item_modified","itemId":"68","quantityAverage":"668.2380952380951","quantityMax":"999","quantityMin":"99"}]
