[{"count":"523","country":"United States","eventName":"item_modified","itemId":"50","quantityAverage":"752.4684512428297","quantityMax":"999","quantityMin":"1"},{"count":"505","country":"Germany","eventName":"item_modified","itemId":"50","quantityAverage":"943.0495049504952","quantityMax":"999","quantityMin":"1"},{"count":"411","country":"Brazil","eventName":"item_modified","itemId":"68","quantityAverage":"506.5036496350365","quantityMax":"999","quantityMin":"1"},{"count":"382","country":"United States","eventName":"item_modified","itemId":"1","quantityAverage":"463.93717277486917","quantityMax":"999","quantityMin":"1"},{"count":"369","country":"Brazil","eventName":"item_modified","itemId":"50","quantityAverage":"626.9295392953928","quantityMax":"999","quantityMin":"1"},{"count":"336","country":"Brazil","eventName":"item_modified","itemId":"1","quantityAverage":"470.16666666666663","quantityMax":"999","quantityMin":"1"},{"count":"323","country":"Spain","eventName":"item_modified","itemId":"50","quantityAverage":"920.8668730650154","quantityMax":"999","quantityMin":"1"},{"count":"285","country":"United States","eventName":"item_modified","itemId":"68","quantityAverage":"576.701754385965","quantityMax":"999","quantityMin":"1"},{"count":"283","country":"Italy","eventName":"item_modified","itemId":"50","quantityAverage":"925.1448763250881","quantityMax":"999","quantityMin":"6"},{"count":"153","country":"Brazil","eventName":"item_modified","itemId":"2","quantityAverage":"472.8235294117648","quantityMax":"999","quantityMin":"3"},{"count":"152","country":"United States","eventName":"item_modified","itemId":"23","quantityAverage":"709.7236842105264","quantityMax":"999","quantityMin":"1"},{"count":"147","country":"United States","eventName":"item_modified","itemId":"2","quantityAverage":"512.3333333333331","quantityMax":"999","quantityMin":"1"},{"count":"141","country":"India","eventName":"item_modified","itemId":"50","quantityAverage":"696.8936170212764","quantityMax":"999","quantityMin":"1"},{"count":"140","country":"Germany","eventName":"item_modified","itemId":"68","quantityAverage":"763.1142857142856","quantityMax":"999","quantityMin":"1"},{"count":"131","country":"United States","eventName":"item_modified","itemId":"84","quantityAverage":"424.8549618320611","quantityMax":"999","quantityMin":"1"},{"count":"129","country":"France","eventName":"item_modified","itemId":"50","quantityAverage":"759.9767441860466","quantityMax":"999","quantityMin":"3"},{"count":"129","country":"Italy","eventName":"item_modified","itemId":"1","quantityAverage":"529.4651162790699","quantityMax":"999","quantityMin":"1"},{"count":"124","country":"United Kingdom","eventName":"item_modified","itemId":"50","quantityAverage":"717.2500000000001","quantityMax":"999","quantityMin":"1"},{"count":"123","country":"Mexico","eventName":"item_modified","itemId":"50","quantityAverage":"818.1138211382116","quantityMax":"999","quantityMin":"10"},{"count":"116","country":"Germany","eventName":"item_modified","itemId":"23","quantityAverage":"945.7758620689656","quantityMax":"999","quantityMin":"1"},{"count":"114","country":"Brazil","eventName":"item_modified","itemId":"23","quantityAverage":"659.061403508772","quantityMax":"999","quantityMin":"1"},{"count":"109","country":"United States","eventName":"item_modified","itemId":"29","quantityAverage":"658.862385321101","quantityMax":"999","quantityMin":"5"},{"count":"107","country":"Italy","eventName":"item_modified","itemId":"77","quantityAverage":"868.1682242990653","quantityMax":"999","quantityMin":"1"},{"count":"107","country":"Italy","eventName":"item_modified","itemId":"68","quantityAverage":"500.35514018691583","quantityMax":"999","quantityMin":"1"},{"count":"105","country":"Germany","eventName":"item_modified","itemId":"77","quantityAverage":"970.1809523809522","quantityMax":"999","quantityMin":"50"},{"count":"100","country":"United States","eventName":"item_modified","itemId":"77","quantityAverage":"742.46","quantityMax":"999","quantityMin":"5"},{"count":"99","country":"India","eventName":"item_modified","itemId":"1","quantityAverage":"609.2525252525253","quantityMax":"999","quantityMin":"1"},{"count":"97","country":"Argentina","eventName":"item_modified","itemId":"50","quantityAverage":"897.5567010309278","quantityMax":"999","quantityMin":"30"},{"count":"97","country":"Brazil","eventName":"item_modified","itemId":"29","quantityAverage":"615.3711340206186","quantityMax":"999","quantityMin":"1"},{"count":"84","country":"Philippines","eventName":"item_modified","itemId":"50","quantityAverage":"754.25","quantityMax":"999","quantityMin":"2"},{"count":"83","country":"Netherlands","eventName":"item_modified","itemId":"50","quantityAverage":"946.4939759036143","quantityMax":"999","quantityMin":"99"},{"count":"82","country":"United Kingdom","eventName":"item_modified","itemId":"1","quantityAverage":"424.0853658536587","quantityMax":"999","quantityMin":"1"},{"count":"82","country":"Spain","eventName":"item_modified","itemId":"1","quantityAverage":"475.3048780487805","quantityMax":"999","quantityMin":"1"},{"count":"81","country":"United States","eventName":"item_modified","itemId":"340","quantityAverage":"20.493827160493833","quantityMax":"999","quantityMin":"1"},{"count":"81","country":"Brazil","eventName":"item_modified","itemId":"84","quantityAverage":"394.5061728395062","quantityMax":"999","quantityMin":"1"},{"count":"81","country":"United States","eventName":"item_modified","itemId":"53","quantityAverage":"591.5432098765432","quantityMax":"999","quantityMin":"10"},{"count":"80","country":"Philippines","eventName":"item_modified","itemId":"1","quantityAverage":"675.825","quantityMax":"999","quantityMin":"2"},{"count":"78","country":"Germany","eventName":"item_modified","itemId":"1","quantityAverage":"534.397435897436","quantityMax":"999","quantityMin":"1"},{"count":"78","country":"Venezuela","eventName":"item_modified","itemId":"50","quantityAverage":"818.4102564102566","quantityMax":"999","quantityMin":"20"},{"count":"77","country":"Brazil","eventName":"item_modified","itemId":"340","quantityAverage":"29.831168831168817","quantityMax":"999","quantityMin":"1"},{"count":"77","country":"France","eventName":"item_modified","itemId":"1","quantityAverage":"361.2857142857143","quantityMax":"999","quantityMin":"1"},{"count":"76","country":"Colombia","eventName":"item_modified","itemId":"50","quantityAverage":"811.5000000000001","quantityMax":"999","quantityMin":"5"},{"count":"75","country":"United States","eventName":"item_modified","itemId":"93","quantityAverage":"293.4533333333333","quantityMax":"999","quantityMin":"1"},{"count":"75","country":"South Korea","eventName":"item_modified","itemId":"1","quantityAverage":"417.9733333333333","quantityMax":"999","quantityMin":"1"},{"count":"75","country":"Canada","eventName":"item_modified","itemId":"50","quantityAverage":"725.4799999999999","quantityMax":"999","quantityMin":"3"},{"count":"74","country":"United States","eventName":"item_modified","itemId":"19","quantityAverage":"551.8783783783783","quantityMax":"999","quantityMin":"1"},{"count":"74","country":"Chile","eventName":"item_modified","itemId":"50","quantityAverage":"850.6756756756756","quantityMax":"999","quantityMin":"15"},{"count":"73","country":"Australia","eventName":"item_modified","itemId":"50","quantityAverage":"821.3698630136985","quantityMax":"999","quantityMin":"20"},{"count":"71","country":"Peru","eventName":"item_modified","itemId":"50","quantityAverage":"664.5211267605633","quantityMax":"999","quantityMin":"1"},{"count":"71","country":"Brazil","eventName":"item_modified","itemId":"77","quantityAverage":"679.4647887323945","quantityMax":"999","quantityMin":"10"},{"count":"70","country":"Brazil","eventName":"item_modified","itemId":"25","quantityAverage":"640.3428571428569","quantityMax":"999","quantityMin":"1"},{"count":"69","country":"United States","eventName":"item_modified","itemId":"25","quantityAverage":"455.99999999999994","quantityMax":"999","quantityMin":"10"},{"count":"68","country":"Brazil","eventName":"item_modified","itemId":"231","quantityAverage":"60.632352941176464","quantityMax":"999","quantityMin":"1"},{"count":"68","country":"Brazil","eventName":"item_modified","itemId":"216","quantityAverage":"166.44117647058823","quantityMax":"999","quantityMin":"1"},{"count":"68","country":"Italy","eventName":"item_modified","itemId":"2","quantityAverage":"526.2794117647059","quantityMax":"999","quantityMin":"1"},{"count":"67","country":"Brazil","eventName":"item_modified","itemId":"353","quantityAverage":"18.55223880597015","quantityMax":"999","quantityMin":"1"},{"count":"66","country":"France","eventName":"item_modified","itemId":"68","quantityAverage":"635.0454545454546","quantityMax":"999","quantityMin":"1"},{"count":"65","country":"Mexico","eventName":"item_modified","itemId":"1","quantityAverage":"618.1846153846155","quantityMax":"999","quantityMin":"1"},{"count":"65","country":"United States","eventName":"item_modified","itemId":"40","quantityAverage":"207.06153846153845","quantityMax":"999","quantityMin":"1"},{"count":"64","country":"United States","eventName":"item_modified","itemId":"41","quantityAverage":"767.984375","quantityMax":"999","quantityMin":"1"},{"count":"64","country":"United States","eventName":"item_modified","itemId":"4","quantityAverage":"388.84375","quantityMax":"999","quantityMin":"2"},{"count":"63","country":"Brazil","eventName":"item_modified","itemId":"24","quantityAverage":"639.1269841269842","quantityMax":"999","quantityMin":"4"},{"count":"63","country":"United States","eventName":"item_modified","itemId":"71","quantityAverage":"393.2063492063492","quantityMax":"999","quantityMin":"0"},{"count":"63","country":"Brazil","eventName":"item_modified","itemId":"110","quantityAverage":"451.8412698412699","quantityMax":"999","quantityMin":"1"},{"count":"62","country":"United Kingdom","eventName":"item_modified","itemId":"68","quantityAverage":"583.7258064516129","quantityMax":"999","quantityMin":"1"},{"count":"62","country":"South Korea","eventName":"item_modified","itemId":"50","quantityAverage":"748.8225806451611","quantityMax":"999","quantityMin":"0"},{"count":"62","country":"Brazil","eventName":"item_modified","itemId":"83","quantityAverage":"208.58064516129033","quantityMax":"999","quantityMin":"1"},{"count":"62","country":"Brazil","eventName":"item_modified","itemId":"351","quantityAverage":"19.209677419354836","quantityMax":"999","quantityMin":"1"},{"count":"61","country":"Brazil","eventName":"item_modified","itemId":"362","quantityAverage":"20.98360655737705","quantityMax":"999","quantityMin":"1"},{"count":"60","country":"Indonesia","eventName":"item_modified","itemId":"1","quantityAverage":"614.3333333333333","quantityMax":"999","quantityMin":"1"},{"count":"60","country":"Brazil","eventName":"item_modified","itemId":"329","quantityAverage":"103.13333333333333","quantityMax":"999","quantityMin":"1"},{"count":"59","country":"Vietnam","eventName":"item_modified","itemId":"50","quantityAverage":"563.0338983050847","quantityMax":"999","quantityMin":"9"},{"count":"59","country":"United States","eventName":"item_modified","itemId":"3","quantityAverage":"305.728813559322","quantityMax":"999","quantityMin":"7"},{"count":"59","country":"United States","eventName":"item_modified","itemId":"158","quantityAverage":"565.7627118644068","quantityMax":"999","quantityMin":"2"},{"count":"59","country":"Brazil","eventName":"item_modified","itemId":"3","quantityAverage":"500.0847457627119","quantityMax":"999","quantityMin":"1"},{"count":"59","country":"Germany","eventName":"item_modified","itemId":"41","quantityAverage":"955.0338983050848","quantityMax":"999","quantityMin":"1"},{"count":"59","country":"Brazil","eventName":"item_modified","itemId":"330","quantityAverage":"105.37288135593222","quantityMax":"999","quantityMin":"1"},{"count":"59","country":"Brazil","eventName":"item_modified","itemId":"53","quantityAverage":"743.8474576271185","quantityMax":"999","quantityMin":"6"},{"count":"58","country":"Spain","eventName":"item_modified","itemId":"68","quantityAverage":"699.4655172413794","quantityMax":"999","quantityMin":"35"},{"count":"58","country":"Brazil","eventName":"item_modified","itemId":"93","quantityAverage":"276.7586206896552","quantityMax":"999","quantityMin":"1"},{"count":"57","country":"United States","eventName":"item_modified","itemId":"216","quantityAverage":"25.26315789473684","quantityMax":"600","quantityMin":"1"},{"count":"57","country":"United States","eventName":"item_modified","itemId":"351","quantityAverage":"27.315789473684198","quantityMax":"999","quantityMin":"1"},{"count":"57","country":"Argentina","eventName":"item_modified","itemId":"68","quantityAverage":"595.8070175438596","quantityMax":"999","quantityMin":"30"},{"count":"56","country":"Indonesia","eventName":"item_modified","itemId":"50","quantityAverage":"876.8392857142856","quantityMax":"999","quantityMin":"5"},{"count":"56","country":"Brazil","eventName":"item_modified","itemId":"82","quantityAverage":"166.85714285714283","quantityMax":"999","quantityMin":"1"},{"count":"56","country":"Brazil","eventName":"item_modified","itemId":"357","quantityAverage":"19.571428571428573","quantityMax":"999","quantityMin":"1"},{"count":"55","country":"United States","eventName":"item_modified","itemId":"197","quantityAverage":"121.94545454545457","quantityMax":"999","quantityMin":"1"},{"count":"54","country":"Brazil","eventName":"item_modified","itemId":"4","quantityAverage":"573.7592592592592","quantityMax":"999","quantityMin":"3"},{"count":"54","country":"Brazil","eventName":"item_modified","itemId":"331","quantityAverage":"114.3148148148148","quantityMax":"999","quantityMin":"1"},{"count":"54","country":"Brazil","eventName":"item_modified","itemId":"107","quantityAverage":"278.48148148148147","quantityMax":"999","quantityMin":"1"},{"count":"53","country":"Italy","eventName":"item_modified","itemId":"84","quantityAverage":"165.88679245283018","quantityMax":"999","quantityMin":"1"},{"count":"53","country":"United States","eventName":"item_modified","itemId":"353","quantityAverage":"27.490566037735842","quantityMax":"999","quantityMin":"1"},{"count":"52","country":"United States","eventName":"item_modified","itemId":"83","quantityAverage":"222.86538461538467","quantityMax":"999","quantityMin":"1"},{"count":"52","country":"Philippines","eventName":"item_modified","itemId":"23","quantityAverage":"732.9999999999999","quantityMax":"999","quantityMin":"25"},{"count":"52","country":"United States","eventName":"item_modified","itemId":"49","quantityAverage":"675.2692307692307","quantityMax":"999","quantityMin":"15"},{"count":"52","country":"Brazil","eventName":"item_modified","itemId":"335","quantityAverage":"99.78846153846156","quantityMax":"999","quantityMin":"1"},{"count":"52","country":"Brazil","eventName":"item_modified","itemId":"71","quantityAverage":"304.1153846153846","quantityMax":"999","quantityMin":"1"},{"count":"51","country":"United States","eventName":"item_modified","itemId":"362","quantityAverage":"30.235294117647065","quantityMax":"999","quantityMin":"1"},{"count":"51","country":"United States","eventName":"item_modified","itemId":"11","quantityAverage":"388.03921568627453","quantityMax":"999","quantityMin":"1"},{"count":"51","country":"Brazil","eventName":"item_modified","itemId":"41","quantityAverage":"745.9607843137254","quantityMax":"999","quantityMin":"10"}]
